reStructuredText/__init__.py
reStructuredText/example.py
restructuredtext-0.0.1.dist-info/METADATA
restructuredtext-0.0.1.dist-info/WHEEL
restructuredtext-0.0.1.dist-info/RECORD
