Metadata-Version: 2.4
Name: reStructuredText
Version: 0.0.1
Summary: A template for projects that will be distributed on PyPI.
Project-URL: Homepage, https://github.com/kaycebasques/reStructuredText
Project-URL: Issues, https://github.com/kaycebasques/reStructuredText/issues
Author-email: Kayce Basques <kaycebasques@gmail.com>
License-Expression: Apache-2.0
Classifier: Operating System :: OS Independent
Classifier: Programming Language :: Python :: 3
Requires-Python: >=3.8
